tscounters/__init__.py
tscounters/aggregator.py
tscounters/counter_engine.py
tscounters/counter_pusher.py
tscounters/counters.py
tscounters_py_nb-0.0.4.dist-info/LICENSE
tscounters_py_nb-0.0.4.dist-info/METADATA
tscounters_py_nb-0.0.4.dist-info/WHEEL
tscounters_py_nb-0.0.4.dist-info/top_level.txt
tscounters_py_nb-0.0.4.dist-info/RECORD
